[
  {
    "name": "Proxmox",
    "category": "tools",
    "description": "Virtualization Management",
    "level": "Beginner",
    "url": "https://www.proxmox.com/",
    "icon": "https://cdn.jsdelivr.net/gh/homarr-labs/dashboard-icons/webp/proxmox.webp",
    "iconAlt": "Proxmox logo"
  },
  {
    "name": "Sliver",
    "category": "tools",
    "description": "C2 Framework",
    "level": "Beginner",
    "url": "https://sliver.sh/",
    "icon": "https://external-content.duckduckgo.com/ip3/sliver.sh.ico",
    "iconAlt": "Sliver logo"
  },
  {
    "name": "Evil-WinRM",
    "category": "tools",
    "description": "Post Exploitation",
    "level": "Beginner",
    "url": "https://github.com/Hackplayers/evil-winrm",
    "icon": "https://www.kali.org/tools/evil-winrm/images/evil-winrm-logo.svg",
    "iconAlt": "Evil-WinRM logo"
  },
  {
    "name": "Metasploit",
    "category": "tools",
    "description": "Exploitation",
    "level": "Intermediate",
    "url": "https://www.metasploit.com/",
    "icon": "https://www.kali.org/tools/metasploit-framework/images/metasploit-framework-logo.svg",
    "iconAlt": "Metasploit logo"
  },
  {
    "name": "NetExec",
    "category": "tools",
    "description": "Network Exploitation",
    "level": "Beginner",
    "url": "https://www.netexec.wiki/",
    "icon": "https://www.kali.org/tools/netexec/images/netexec-logo.svg",
    "iconAlt": "NetExec logo"
  },
  {
    "name": "FFuf",
    "category": "tools",
    "description": "Fuffing/Fuzzing",
    "level": "Beginner",
    "url": "https://github.com/ffuf/ffuf",
    "icon": "assets/ffuf_waving_250.png",
    "iconAlt": "FFuf logo"
  },
  {
    "name": "NMAP",
    "category": "tools",
    "description": "Enumeration",
    "level": "Intermediate",
    "url": "https://www.nmap.org/",
    "icon": "https://img.icons8.com/?size=100&id=9b5wowKIlo9d&format=png&color=000000",
    "iconAlt": "NMAP logo"
  },
  {
    "name": "Ghidra",
    "category": "tools",
    "description": "Reverse Engineering",
    "level": "Beginner",
    "url": "https://ghidra-sre.org/",
    "icon": "https://www.kali.org/tools/ghidra/images/ghidra-logo.svg",
    "iconAlt": "Ghidra logo"
  },
  {
    "name": "NetCat",
    "category": "tools",
    "description": "Back-end Network Tool",
    "level": "Beginner",
    "url": "https://www.kali.org/tools/netcat/",
    "icon": "https://www.kali.org/tools/netcat/images/netcat-logo.svg",
    "iconAlt": "NetCat logo"
  },
  {
    "name": "MS Azure",
    "category": "tools",
    "description": "Cloud platform",
    "level": "Beginner",
    "url": "https://azure.microsoft.com/en-us",
    "icon": "https://cdn.jsdelivr.net/gh/homarr-labs/dashboard-icons/webp/microsoft-azure.webp",
    "iconAlt": "MS Azure logo"
  },
  {
    "name": "Docker",
    "category": "tools",
    "description": "Containerization",
    "level": "Beginner",
    "url": "https://www.docker.com/",
    "icon": "https://cdn.jsdelivr.net/gh/homarr-labs/dashboard-icons/webp/docker.webp",
    "iconAlt": "Docker logo"
  },
  {
    "name": "JavaScript",
    "category": "languages",
    "description": "Programming Language",
    "level": "Beginner",
    "url": "https://developer.mozilla.org/en-US/docs/Web/JavaScript",
    "icon": "https://cdn.jsdelivr.net/gh/homarr-labs/dashboard-icons/webp/javascript.webp",
    "iconAlt": "JavaScript logo"
  },
  {
    "name": "Python",
    "category": "languages",
    "description": "Programming Language",
    "level": "Beginner",
    "url": "https://www.python.org/",
    "icon": "https://cdn.jsdelivr.net/gh/homarr-labs/dashboard-icons/webp/python.webp",
    "iconAlt": "Python logo"
  },
  {
    "name": "HTML",
    "category": "languages",
    "description": "Markup Language",
    "level": "Expert",
    "url": "https://developer.mozilla.org/en-US/docs/Web/HTML",
    "icon": "https://cdn.jsdelivr.net/gh/homarr-labs/dashboard-icons/webp/html-light.webp",
    "iconAlt": "HTML logo"
  },
  {
    "name": "CSS",
    "category": "languages",
    "description": "Markup Language",
    "level": "Advanced",
    "url": "https://developer.mozilla.org/en-US/docs/Web/CSS",
    "icon": "https://cdn.jsdelivr.net/gh/homarr-labs/dashboard-icons/webp/css-light.webp",
    "iconAlt": "CSS logo"
  },
  {
    "name": "Wireshark",
    "category": "tools",
    "description": "Network Protocol Analyzer",
    "level": "Intermediate",
    "url": "https://www.wireshark.org/",
    "icon": "https://cdn.jsdelivr.net/gh/homarr-labs/dashboard-icons/webp/wireshark.webp",
    "iconAlt": "Wireshark logo"
  },
  {
    "name": "Hashcat",
    "category": "tools",
    "description": "Password Cracking",
    "level": "Intermediate",
    "url": "https://hashcat.net/",
    "icon": "https://hashcat.net/s/i/hashcat-icon.png",
    "iconAlt": "Hashcat logo"
  },
  {
    "name": "John The Ripper",
    "category": "tools",
    "description": "Password Cracking",
    "level": "Intermediate",
    "url": "https://www.openwall.com/john/",
    "icon": "https://www.kali.org/tools/john/images/john-logo.svg",
    "iconAlt": "John The Ripper logo"
  },
  {
    "name": "ZAP Proxy",
    "category": "tools",
    "description": "Web Application Security Scanner",
    "level": "Beginner",
    "url": "https://www.zaproxy.org/",
    "icon": "https://www.kali.org/tools/zaproxy/images/zaproxy-logo.svg",
    "iconAlt": "ZAP Proxy logo"
  }
]